[
    {
        "report_timestamp_utc": "2025-10-18T14:37:34.338712+00:00",
        "hot_topics": [],
        "sentiment_analysis": {
            "average_score": 0.06675061224489798,
            "positive_percent": 35.51020408163265,
            "negative_percent": 24.897959183673468,
            "neutral_percent": 39.59183673469388,
            "most_positive_example": {
                "text": "finally ran O&O's Shut Up 10 today and i'm happy to be even a little more free of Win 11's spyware bloat. <3",
                "user": "snoodoodle",
                "score": 0.9322
            },
            "most_negative_example": {
                "text": "MY STOMACH HURTS SO BAD FAWWKK This feels like a personal attack on me as a person SLASH REF :/",
                "user": "sunsua",
                "score": -0.9425
            }
        },
        "summary_message": "No phrases met the trending threshold."
    },
    {
        "report_timestamp_utc": "2025-10-19T03:32:22.921981+00:00",
        "hot_topics": [],
        "sentiment_analysis": {
            "average_score": 0.08986260162601627,
            "positive_percent": 38.482384823848236,
            "negative_percent": 22.22222222222222,
            "neutral_percent": 39.295392953929536,
            "most_positive_example": {
                "text": "finally ran O&O's Shut Up 10 today and i'm happy to be even a little more free of Win 11's spyware bloat. <3",
                "user": "snoodoodle",
                "score": 0.9322
            },
            "most_negative_example": {
                "text": "MY STOMACH HURTS SO BAD FAWWKK This feels like a personal attack on me as a person SLASH REF :/",
                "user": "sunsua",
                "score": -0.9425
            }
        },
        "summary_message": "No phrases met the trending threshold."
    },
    {
        "report_timestamp_utc": "2025-10-19T14:37:29.086069+00:00",
        "hot_topics": [],
        "sentiment_analysis": {
            "average_score": 0.07743752860411901,
            "positive_percent": 36.38443935926773,
            "negative_percent": 22.883295194508012,
            "neutral_percent": 40.73226544622426,
            "most_positive_example": {
                "text": "finally ran O&O's Shut Up 10 today and i'm happy to be even a little more free of Win 11's spyware bloat. <3",
                "user": "snoodoodle",
                "score": 0.9322
            },
            "most_negative_example": {
                "text": "MY STOMACH HURTS SO BAD FAWWKK This feels like a personal attack on me as a person SLASH REF :/",
                "user": "sunsua",
                "score": -0.9425
            }
        },
        "summary_message": "No phrases met the trending threshold."
    },
    {
        "report_timestamp_utc": "2025-10-20T03:34:19.071103+00:00",
        "hot_topics": [],
        "sentiment_analysis": {
            "average_score": 0.06894324786324786,
            "positive_percent": 35.21367521367522,
            "negative_percent": 23.931623931623932,
            "neutral_percent": 40.85470085470085,
            "most_positive_example": {
                "text": "finally ran O&O's Shut Up 10 today and i'm happy to be even a little more free of Win 11's spyware bloat. <3",
                "user": "snoodoodle",
                "score": 0.9322
            },
            "most_negative_example": {
                "text": "MY STOMACH HURTS SO BAD FAWWKK This feels like a personal attack on me as a person SLASH REF :/",
                "user": "sunsua",
                "score": -0.9425
            }
        },
        "summary_message": "No phrases met the trending threshold."
    },
    {
        "report_timestamp_utc": "2025-10-20T14:42:35.811176+00:00",
        "hot_topics": [],
        "sentiment_analysis": {
            "average_score": 0.06978534743202416,
            "positive_percent": 35.04531722054381,
            "negative_percent": 23.564954682779458,
            "neutral_percent": 41.389728096676734,
            "most_positive_example": {
                "text": "finally ran O&O's Shut Up 10 today and i'm happy to be even a little more free of Win 11's spyware bloat. <3",
                "user": "snoodoodle",
                "score": 0.9322
            },
            "most_negative_example": {
                "text": "MY STOMACH HURTS SO BAD FAWWKK This feels like a personal attack on me as a person SLASH REF :/",
                "user": "sunsua",
                "score": -0.9425
            }
        },
        "summary_message": "No phrases met the trending threshold."
    },
    {
        "report_timestamp_utc": "2025-10-21T03:26:29.405181+00:00",
        "hot_topics": [],
        "sentiment_analysis": {
            "average_score": 0.06181768292682927,
            "positive_percent": 34.8780487804878,
            "negative_percent": 24.268292682926827,
            "neutral_percent": 40.853658536585364,
            "most_positive_example": {
                "text": "package arrived I’m so happy :D <- me being happy",
                "user": "mothpanic",
                "score": 0.9412
            },
            "most_negative_example": {
                "text": "big bang theory blart mall cop fuck ass slap goddamn shit fuck",
                "user": "wormsauce",
                "score": -0.9485
            }
        },
        "summary_message": "No phrases met the trending threshold."
    },
    {
        "report_timestamp_utc": "2025-10-21T14:41:43.666074+00:00",
        "hot_topics": [],
        "sentiment_analysis": {
            "average_score": 0.06369192477876107,
            "positive_percent": 34.73451327433628,
            "negative_percent": 23.893805309734514,
            "neutral_percent": 41.3716814159292,
            "most_positive_example": {
                "text": "package arrived I’m so happy :D <- me being happy",
                "user": "mothpanic",
                "score": 0.9412
            },
            "most_negative_example": {
                "text": "big bang theory blart mall cop fuck ass slap goddamn shit fuck",
                "user": "wormsauce",
                "score": -0.9485
            }
        },
        "summary_message": "No phrases met the trending threshold."
    },
    {
        "report_timestamp_utc": "2025-10-22T03:30:27.145276+00:00",
        "hot_topics": [],
        "sentiment_analysis": {
            "average_score": 0.061983714285714295,
            "positive_percent": 34.285714285714285,
            "negative_percent": 23.904761904761905,
            "neutral_percent": 41.80952380952381,
            "most_positive_example": {
                "text": "package arrived I’m so happy :D <- me being happy",
                "user": "mothpanic",
                "score": 0.9412
            },
            "most_negative_example": {
                "text": "big bang theory blart mall cop fuck ass slap goddamn shit fuck",
                "user": "wormsauce",
                "score": -0.9485
            }
        },
        "summary_message": "No phrases met the trending threshold."
    },
    {
        "report_timestamp_utc": "2025-10-22T14:47:03.950208+00:00",
        "hot_topics": [],
        "sentiment_analysis": {
            "average_score": 0.0577253982300885,
            "positive_percent": 33.98230088495575,
            "negative_percent": 24.513274336283185,
            "neutral_percent": 41.50442477876106,
            "most_positive_example": {
                "text": "package arrived I’m so happy :D <- me being happy",
                "user": "mothpanic",
                "score": 0.9412
            },
            "most_negative_example": {
                "text": "big bang theory blart mall cop fuck ass slap goddamn shit fuck",
                "user": "wormsauce",
                "score": -0.9485
            }
        },
        "summary_message": "No phrases met the trending threshold."
    },
    {
        "report_timestamp_utc": "2025-10-23T03:15:34.578135+00:00",
        "hot_topics": [],
        "sentiment_analysis": {
            "average_score": 0.0586748417721519,
            "positive_percent": 33.54430379746836,
            "negative_percent": 24.446202531645568,
            "neutral_percent": 42.00949367088608,
            "most_positive_example": {
                "text": "package arrived I’m so happy :D <- me being happy",
                "user": "mothpanic",
                "score": 0.9412
            },
            "most_negative_example": {
                "text": "big bang theory blart mall cop fuck ass slap goddamn shit fuck",
                "user": "wormsauce",
                "score": -0.9485
            }
        },
        "summary_message": "No phrases met the trending threshold."
    },
    {
        "report_timestamp_utc": "2025-10-23T14:44:33.294327+00:00",
        "hot_topics": [],
        "sentiment_analysis": {
            "average_score": 0.060578602941176465,
            "positive_percent": 33.75,
            "negative_percent": 23.823529411764703,
            "neutral_percent": 42.42647058823529,
            "most_positive_example": {
                "text": "package arrived I’m so happy :D <- me being happy",
                "user": "mothpanic",
                "score": 0.9412
            },
            "most_negative_example": {
                "text": "big bang theory blart mall cop fuck ass slap goddamn shit fuck",
                "user": "wormsauce",
                "score": -0.9485
            }
        },
        "summary_message": "No phrases met the trending threshold."
    },
    {
        "report_timestamp_utc": "2025-10-24T03:12:14.617370+00:00",
        "hot_topics": [],
        "sentiment_analysis": {
            "average_score": 0.06031575067024129,
            "positive_percent": 33.9142091152815,
            "negative_percent": 24.06166219839142,
            "neutral_percent": 42.024128686327074,
            "most_positive_example": {
                "text": "package arrived I’m so happy :D <- me being happy",
                "user": "mothpanic",
                "score": 0.9412
            },
            "most_negative_example": {
                "text": "big bang theory blart mall cop fuck ass slap goddamn shit fuck",
                "user": "wormsauce",
                "score": -0.9485
            }
        },
        "summary_message": "No phrases met the trending threshold."
    },
    {
        "report_timestamp_utc": "2025-10-24T14:44:09.375528+00:00",
        "hot_topics": [],
        "sentiment_analysis": {
            "average_score": 0.06041010101010101,
            "positive_percent": 33.90151515151515,
            "negative_percent": 23.92676767676768,
            "neutral_percent": 42.17171717171717,
            "most_positive_example": {
                "text": "package arrived I’m so happy :D <- me being happy",
                "user": "mothpanic",
                "score": 0.9412
            },
            "most_negative_example": {
                "text": "big bang theory blart mall cop fuck ass slap goddamn shit fuck",
                "user": "wormsauce",
                "score": -0.9485
            }
        },
        "summary_message": "No phrases met the trending threshold."
    },
    {
        "report_timestamp_utc": "2025-10-25T03:14:54.572700+00:00",
        "hot_topics": [],
        "sentiment_analysis": {
            "average_score": 0.05866459189665296,
            "positive_percent": 34.05754550792719,
            "negative_percent": 24.13388138578978,
            "neutral_percent": 41.808573106283035,
            "most_positive_example": {
                "text": "package arrived I’m so happy :D <- me being happy",
                "user": "mothpanic",
                "score": 0.9412
            },
            "most_negative_example": {
                "text": "big bang theory blart mall cop fuck ass slap goddamn shit fuck",
                "user": "wormsauce",
                "score": -0.9485
            }
        },
        "summary_message": "No phrases met the trending threshold."
    },
    {
        "report_timestamp_utc": "2025-10-25T14:38:13.518877+00:00",
        "hot_topics": [],
        "sentiment_analysis": {
            "average_score": 0.05841179775280899,
            "positive_percent": 34.044943820224724,
            "negative_percent": 24.044943820224717,
            "neutral_percent": 41.91011235955056,
            "most_positive_example": {
                "text": "package arrived I’m so happy :D <- me being happy",
                "user": "mothpanic",
                "score": 0.9412
            },
            "most_negative_example": {
                "text": "big bang theory blart mall cop fuck ass slap goddamn shit fuck",
                "user": "wormsauce",
                "score": -0.9485
            }
        },
        "summary_message": "No phrases met the trending threshold."
    },
    {
        "report_timestamp_utc": "2025-10-26T03:27:39.895119+00:00",
        "hot_topics": [],
        "sentiment_analysis": {
            "average_score": 0.06141302966101695,
            "positive_percent": 34.74576271186441,
            "negative_percent": 24.046610169491526,
            "neutral_percent": 41.20762711864407,
            "most_positive_example": {
                "text": "package arrived I’m so happy :D <- me being happy",
                "user": "mothpanic",
                "score": 0.9412
            },
            "most_negative_example": {
                "text": "big bang theory blart mall cop fuck ass slap goddamn shit fuck",
                "user": "wormsauce",
                "score": -0.9485
            }
        },
        "summary_message": "No phrases met the trending threshold."
    },
    {
        "report_timestamp_utc": "2025-10-26T14:38:35.882758+00:00",
        "hot_topics": [],
        "sentiment_analysis": {
            "average_score": 0.0605551971326165,
            "positive_percent": 34.66461853558628,
            "negative_percent": 24.372759856630825,
            "neutral_percent": 40.9626216077829,
            "most_positive_example": {
                "text": "i love theatre i love my best friends i love my bf i love being so fucking tired",
                "user": "appledanish",
                "score": 0.9706
            },
            "most_negative_example": {
                "text": "big bang theory blart mall cop fuck ass slap goddamn shit fuck",
                "user": "wormsauce",
                "score": -0.9485
            }
        },
        "summary_message": "No phrases met the trending threshold."
    },
    {
        "report_timestamp_utc": "2025-10-27T03:38:00.282349+00:00",
        "hot_topics": [],
        "sentiment_analysis": {
            "average_score": 0.06037106796116506,
            "positive_percent": 34.56310679611651,
            "negative_percent": 24.368932038834952,
            "neutral_percent": 41.067961165048544,
            "most_positive_example": {
                "text": "AAAAAAHHHHHHHH!! I LOVE YOU I LOVE YOU I LOVE YOU I LOVE YOU I LOVE YOU!!!!!",
                "user": "serafinisdead",
                "score": 0.9755
            },
            "most_negative_example": {
                "text": "big bang theory blart mall cop fuck ass slap goddamn shit fuck",
                "user": "wormsauce",
                "score": -0.9485
            }
        },
        "summary_message": "No phrases met the trending threshold."
    },
    {
        "report_timestamp_utc": "2025-10-27T14:45:24.363548+00:00",
        "hot_topics": [],
        "sentiment_analysis": {
            "average_score": 0.05983327076489912,
            "positive_percent": 34.3969967151572,
            "negative_percent": 24.401689347724073,
            "neutral_percent": 41.20131393711872,
            "most_positive_example": {
                "text": "AAAAAAHHHHHHHH!! I LOVE YOU I LOVE YOU I LOVE YOU I LOVE YOU I LOVE YOU!!!!!",
                "user": "serafinisdead",
                "score": 0.9755
            },
            "most_negative_example": {
                "text": "it's all my fault it's all my fault it's all my fault it's all my fault it's all my fault it's all my fault it's all my fault",
                "user": "wolfsbane",
                "score": -0.9509
            }
        },
        "summary_message": "No phrases met the trending threshold."
    },
    {
        "report_timestamp_utc": "2025-10-28T03:27:49.498480+00:00",
        "hot_topics": [],
        "sentiment_analysis": {
            "average_score": 0.06157048748353096,
            "positive_percent": 34.51910408432148,
            "negative_percent": 24.19850680720246,
            "neutral_percent": 41.28238910847607,
            "most_positive_example": {
                "text": "AAAAAAHHHHHHHH!! I LOVE YOU I LOVE YOU I LOVE YOU I LOVE YOU I LOVE YOU!!!!!",
                "user": "serafinisdead",
                "score": 0.9755
            },
            "most_negative_example": {
                "text": "it's all my fault it's all my fault it's all my fault it's all my fault it's all my fault it's all my fault it's all my fault",
                "user": "wolfsbane",
                "score": -0.9509
            }
        },
        "summary_message": "No phrases met the trending threshold."
    },
    {
        "report_timestamp_utc": "2025-10-28T14:44:53.815834+00:00",
        "hot_topics": [],
        "sentiment_analysis": {
            "average_score": 0.05988487147071218,
            "positive_percent": 34.344711335861774,
            "negative_percent": 24.27307206068268,
            "neutral_percent": 41.38221660345554,
            "most_positive_example": {
                "text": "AAAAAAHHHHHHHH!! I LOVE YOU I LOVE YOU I LOVE YOU I LOVE YOU I LOVE YOU!!!!!",
                "user": "serafinisdead",
                "score": 0.9755
            },
            "most_negative_example": {
                "text": "i hate hate HATE drawing shit out like can we get this shit over with already?? i don't have the time for this!!!!!!!!!!!!!",
                "user": "catskulls",
                "score": -0.9641
            }
        },
        "summary_message": "No phrases met the trending threshold."
    },
    {
        "report_timestamp_utc": "2025-10-29T03:33:48.549356+00:00",
        "hot_topics": [],
        "sentiment_analysis": {
            "average_score": 0.060673215717722544,
            "positive_percent": 34.40256615878107,
            "negative_percent": 24.137931034482758,
            "neutral_percent": 41.45950280673617,
            "most_positive_example": {
                "text": "AAAAAAHHHHHHHH!! I LOVE YOU I LOVE YOU I LOVE YOU I LOVE YOU I LOVE YOU!!!!!",
                "user": "serafinisdead",
                "score": 0.9755
            },
            "most_negative_example": {
                "text": "i hate hate HATE drawing shit out like can we get this shit over with already?? i don't have the time for this!!!!!!!!!!!!!",
                "user": "catskulls",
                "score": -0.9641
            }
        },
        "summary_message": "No phrases met the trending threshold."
    },
    {
        "report_timestamp_utc": "2025-10-29T14:45:13.723954+00:00",
        "hot_topics": [],
        "sentiment_analysis": {
            "average_score": 0.0617258077072791,
            "positive_percent": 34.64383028415726,
            "negative_percent": 24.094978590891397,
            "neutral_percent": 41.26119112495134,
            "most_positive_example": {
                "text": "AAAAAAHHHHHHHH!! I LOVE YOU I LOVE YOU I LOVE YOU I LOVE YOU I LOVE YOU!!!!!",
                "user": "serafinisdead",
                "score": 0.9755
            },
            "most_negative_example": {
                "text": "i hate hate HATE drawing shit out like can we get this shit over with already?? i don't have the time for this!!!!!!!!!!!!!",
                "user": "catskulls",
                "score": -0.9641
            }
        },
        "summary_message": "No phrases met the trending threshold."
    },
    {
        "report_timestamp_utc": "2025-10-30T03:29:53.747510+00:00",
        "hot_topics": [],
        "sentiment_analysis": {
            "average_score": 0.061840266469282014,
            "positive_percent": 34.6039970392302,
            "negative_percent": 23.982235381199114,
            "neutral_percent": 41.41376757957069,
            "most_positive_example": {
                "text": "AAAAAAHHHHHHHH!! I LOVE YOU I LOVE YOU I LOVE YOU I LOVE YOU I LOVE YOU!!!!!",
                "user": "serafinisdead",
                "score": 0.9755
            },
            "most_negative_example": {
                "text": "i hate hate HATE drawing shit out like can we get this shit over with already?? i don't have the time for this!!!!!!!!!!!!!",
                "user": "catskulls",
                "score": -0.9641
            }
        },
        "summary_message": "No phrases met the trending threshold."
    },
    {
        "report_timestamp_utc": "2025-10-30T14:44:31.820030+00:00",
        "hot_topics": [],
        "sentiment_analysis": {
            "average_score": 0.0626786355475763,
            "positive_percent": 34.68581687612208,
            "negative_percent": 23.949730700179533,
            "neutral_percent": 41.36445242369838,
            "most_positive_example": {
                "text": "AAAAAAHHHHHHHH!! I LOVE YOU I LOVE YOU I LOVE YOU I LOVE YOU I LOVE YOU!!!!!",
                "user": "serafinisdead",
                "score": 0.9755
            },
            "most_negative_example": {
                "text": "i hate hate HATE drawing shit out like can we get this shit over with already?? i don't have the time for this!!!!!!!!!!!!!",
                "user": "catskulls",
                "score": -0.9641
            }
        },
        "summary_message": "No phrases met the trending threshold."
    },
    {
        "report_timestamp_utc": "2025-10-31T03:30:35.197316+00:00",
        "hot_topics": [],
        "sentiment_analysis": {
            "average_score": 0.06194387824897401,
            "positive_percent": 34.575923392612864,
            "negative_percent": 24.110807113543093,
            "neutral_percent": 41.313269493844054,
            "most_positive_example": {
                "text": "AAAAAAHHHHHHHH!! I LOVE YOU I LOVE YOU I LOVE YOU I LOVE YOU I LOVE YOU!!!!!",
                "user": "serafinisdead",
                "score": 0.9755
            },
            "most_negative_example": {
                "text": "i hate hate HATE drawing shit out like can we get this shit over with already?? i don't have the time for this!!!!!!!!!!!!!",
                "user": "catskulls",
                "score": -0.9641
            }
        },
        "summary_message": "No phrases met the trending threshold."
    },
    {
        "report_timestamp_utc": "2025-10-31T14:43:36.371686+00:00",
        "hot_topics": [],
        "sentiment_analysis": {
            "average_score": 0.06592817089452603,
            "positive_percent": 35.01335113484646,
            "negative_percent": 23.865153538050734,
            "neutral_percent": 41.1214953271028,
            "most_positive_example": {
                "text": "AAAAAAHHHHHHHH!! I LOVE YOU I LOVE YOU I LOVE YOU I LOVE YOU I LOVE YOU!!!!!",
                "user": "serafinisdead",
                "score": 0.9755
            },
            "most_negative_example": {
                "text": "i hate hate HATE drawing shit out like can we get this shit over with already?? i don't have the time for this!!!!!!!!!!!!!",
                "user": "catskulls",
                "score": -0.9641
            }
        },
        "summary_message": "No phrases met the trending threshold."
    },
    {
        "report_timestamp_utc": "2025-11-01T03:29:36.496361+00:00",
        "hot_topics": [],
        "sentiment_analysis": {
            "average_score": 0.07378598409542744,
            "positive_percent": 35.95096090125911,
            "negative_percent": 23.658051689860834,
            "neutral_percent": 40.39098740888005,
            "most_positive_example": {
                "text": "AAAAAAHHHHHHHH!! I LOVE YOU I LOVE YOU I LOVE YOU I LOVE YOU I LOVE YOU!!!!!",
                "user": "serafinisdead",
                "score": 0.9755
            },
            "most_negative_example": {
                "text": "i hate hate HATE drawing shit out like can we get this shit over with already?? i don't have the time for this!!!!!!!!!!!!!",
                "user": "catskulls",
                "score": -0.9641
            }
        },
        "summary_message": "No phrases met the trending threshold."
    },
    {
        "report_timestamp_utc": "2025-11-01T14:37:51.120992+00:00",
        "hot_topics": [],
        "sentiment_analysis": {
            "average_score": 0.07697132959419332,
            "positive_percent": 36.32464533157374,
            "negative_percent": 23.325635103926096,
            "neutral_percent": 40.34971956450016,
            "most_positive_example": {
                "text": "AAAAAAHHHHHHHH!! I LOVE YOU I LOVE YOU I LOVE YOU I LOVE YOU I LOVE YOU!!!!!",
                "user": "serafinisdead",
                "score": 0.9755
            },
            "most_negative_example": {
                "text": "i hate hate HATE drawing shit out like can we get this shit over with already?? i don't have the time for this!!!!!!!!!!!!!",
                "user": "catskulls",
                "score": -0.9641
            }
        },
        "summary_message": "No phrases met the trending threshold."
    },
    {
        "report_timestamp_utc": "2025-11-02T03:32:28.694353+00:00",
        "hot_topics": [],
        "sentiment_analysis": {
            "average_score": 0.07578663835347926,
            "positive_percent": 36.16465207448547,
            "negative_percent": 23.58706305129043,
            "neutral_percent": 40.24828487422411,
            "most_positive_example": {
                "text": "AAAAAAHHHHHHHH!! I LOVE YOU I LOVE YOU I LOVE YOU I LOVE YOU I LOVE YOU!!!!!",
                "user": "serafinisdead",
                "score": 0.9755
            },
            "most_negative_example": {
                "text": "i hate hate HATE drawing shit out like can we get this shit over with already?? i don't have the time for this!!!!!!!!!!!!!",
                "user": "catskulls",
                "score": -0.9641
            }
        },
        "summary_message": "No phrases met the trending threshold."
    },
    {
        "report_timestamp_utc": "2025-11-02T14:37:41.797323+00:00",
        "hot_topics": [],
        "sentiment_analysis": {
            "average_score": 0.07754078520441272,
            "positive_percent": 36.340038935756006,
            "negative_percent": 23.42634652822842,
            "neutral_percent": 40.23361453601557,
            "most_positive_example": {
                "text": "AAAAAAHHHHHHHH!! I LOVE YOU I LOVE YOU I LOVE YOU I LOVE YOU I LOVE YOU!!!!!",
                "user": "serafinisdead",
                "score": 0.9755
            },
            "most_negative_example": {
                "text": "i hate hate HATE drawing shit out like can we get this shit over with already?? i don't have the time for this!!!!!!!!!!!!!",
                "user": "catskulls",
                "score": -0.9641
            }
        },
        "summary_message": "No phrases met the trending threshold."
    },
    {
        "report_timestamp_utc": "2025-11-03T03:36:26.452980+00:00",
        "hot_topics": [],
        "sentiment_analysis": {
            "average_score": 0.07813948315341838,
            "positive_percent": 36.539090611710826,
            "negative_percent": 23.290807981681386,
            "neutral_percent": 40.170101406607785,
            "most_positive_example": {
                "text": "AAAAAAHHHHHHHH!! I LOVE YOU I LOVE YOU I LOVE YOU I LOVE YOU I LOVE YOU!!!!!",
                "user": "serafinisdead",
                "score": 0.9755
            },
            "most_negative_example": {
                "text": "i hate hate HATE drawing shit out like can we get this shit over with already?? i don't have the time for this!!!!!!!!!!!!!",
                "user": "catskulls",
                "score": -0.9641
            }
        },
        "summary_message": "No phrases met the trending threshold."
    },
    {
        "report_timestamp_utc": "2025-11-03T14:44:26.541889+00:00",
        "hot_topics": [],
        "sentiment_analysis": {
            "average_score": 0.07687875613747953,
            "positive_percent": 36.56301145662848,
            "negative_percent": 23.600654664484452,
            "neutral_percent": 39.83633387888707,
            "most_positive_example": {
                "text": "AAAAAAHHHHHHHH!! I LOVE YOU I LOVE YOU I LOVE YOU I LOVE YOU I LOVE YOU!!!!!",
                "user": "serafinisdead",
                "score": 0.9755
            },
            "most_negative_example": {
                "text": "i hate hate HATE drawing shit out like can we get this shit over with already?? i don't have the time for this!!!!!!!!!!!!!",
                "user": "catskulls",
                "score": -0.9641
            }
        },
        "summary_message": "No phrases met the trending threshold."
    },
    {
        "report_timestamp_utc": "2025-11-04T03:29:15.709012+00:00",
        "hot_topics": [],
        "sentiment_analysis": {
            "average_score": 0.07715735923608824,
            "positive_percent": 36.61508067171551,
            "negative_percent": 23.575897267039842,
            "neutral_percent": 39.80902206124465,
            "most_positive_example": {
                "text": "AAAAAAHHHHHHHH!! I LOVE YOU I LOVE YOU I LOVE YOU I LOVE YOU I LOVE YOU!!!!!",
                "user": "serafinisdead",
                "score": 0.9755
            },
            "most_negative_example": {
                "text": "i hate hate HATE drawing shit out like can we get this shit over with already?? i don't have the time for this!!!!!!!!!!!!!",
                "user": "catskulls",
                "score": -0.9641
            }
        },
        "summary_message": "No phrases met the trending threshold."
    },
    {
        "report_timestamp_utc": "2025-11-04T14:44:53.025647+00:00",
        "hot_topics": [],
        "sentiment_analysis": {
            "average_score": 0.0768442098317387,
            "positive_percent": 36.621577037281426,
            "negative_percent": 23.68855163312438,
            "neutral_percent": 39.6898713295942,
            "most_positive_example": {
                "text": "AAAAAAHHHHHHHH!! I LOVE YOU I LOVE YOU I LOVE YOU I LOVE YOU I LOVE YOU!!!!!",
                "user": "serafinisdead",
                "score": 0.9755
            },
            "most_negative_example": {
                "text": "i hate hate HATE drawing shit out like can we get this shit over with already?? i don't have the time for this!!!!!!!!!!!!!",
                "user": "catskulls",
                "score": -0.9641
            }
        },
        "summary_message": "No phrases met the trending threshold."
    },
    {
        "report_timestamp_utc": "2025-11-05T03:30:12.180410+00:00",
        "hot_topics": [],
        "sentiment_analysis": {
            "average_score": 0.07988553107530418,
            "positive_percent": 37.06017757316672,
            "negative_percent": 23.544886550476818,
            "neutral_percent": 39.39493587635646,
            "most_positive_example": {
                "text": "AAAAAAHHHHHHHH!! I LOVE YOU I LOVE YOU I LOVE YOU I LOVE YOU I LOVE YOU!!!!!",
                "user": "serafinisdead",
                "score": 0.9755
            },
            "most_negative_example": {
                "text": "i hate hate HATE drawing shit out like can we get this shit over with already?? i don't have the time for this!!!!!!!!!!!!!",
                "user": "catskulls",
                "score": -0.9641
            }
        },
        "summary_message": "No phrases met the trending threshold."
    },
    {
        "report_timestamp_utc": "2025-11-05T14:44:39.782068+00:00",
        "hot_topics": [],
        "sentiment_analysis": {
            "average_score": 0.08089045889732585,
            "positive_percent": 37.14097061736547,
            "negative_percent": 23.374050841862,
            "neutral_percent": 39.48497854077253,
            "most_positive_example": {
                "text": "AAAAAAHHHHHHHH!! I LOVE YOU I LOVE YOU I LOVE YOU I LOVE YOU I LOVE YOU!!!!!",
                "user": "serafinisdead",
                "score": 0.9755
            },
            "most_negative_example": {
                "text": "i hate hate HATE drawing shit out like can we get this shit over with already?? i don't have the time for this!!!!!!!!!!!!!",
                "user": "catskulls",
                "score": -0.9641
            }
        },
        "summary_message": "No phrases met the trending threshold."
    },
    {
        "report_timestamp_utc": "2025-11-06T03:33:27.972536+00:00",
        "hot_topics": [],
        "sentiment_analysis": {
            "average_score": 0.08043401720714759,
            "positive_percent": 37.227001985440104,
            "negative_percent": 23.59364659166115,
            "neutral_percent": 39.17935142289875,
            "most_positive_example": {
                "text": "AAAAAAHHHHHHHH!! I LOVE YOU I LOVE YOU I LOVE YOU I LOVE YOU I LOVE YOU!!!!!",
                "user": "serafinisdead",
                "score": 0.9755
            },
            "most_negative_example": {
                "text": "just gotta kill myself.. just gotta kill myself... just gotta kill myself.. just gotta kill myself... just gotta kill myself.. just gotta ki",
                "user": "anabolicfrolic",
                "score": -0.9788
            }
        },
        "summary_message": "No phrases met the trending threshold."
    },
    {
        "report_timestamp_utc": "2025-11-06T14:44:20.807755+00:00",
        "hot_topics": [],
        "sentiment_analysis": {
            "average_score": 0.08314518493835388,
            "positive_percent": 37.52082639120293,
            "negative_percent": 23.625458180606465,
            "neutral_percent": 38.853715428190604,
            "most_positive_example": {
                "text": "AAAAAAHHHHHHHH!! I LOVE YOU I LOVE YOU I LOVE YOU I LOVE YOU I LOVE YOU!!!!!",
                "user": "serafinisdead",
                "score": 0.9755
            },
            "most_negative_example": {
                "text": "just gotta kill myself.. just gotta kill myself... just gotta kill myself.. just gotta kill myself... just gotta kill myself.. just gotta ki",
                "user": "anabolicfrolic",
                "score": -0.9788
            }
        },
        "summary_message": "No phrases met the trending threshold."
    }
]